<?xml version="1.0" ?>
<Template>
  <Length type="float" default="10" description="" />
  <Width type="float" default="15" description="" />
  <Height type="float" default="15" description="" />
  <MaximumBalls type="float" default="10" description="Maximum Amount of Mercury Balls the pool can generate at once." />
  <HitsBeforeBurst type="float" default="5" description="How many times the balls from this pool can be hit before bursting." />
  <Friction type="float" default="0.1" description="Something to do with the friction of the balls?" />
  <AirFriction type="float" default="0.99" description="Something to do with the friction of the balls?" />
  <Velocity type="float" default="1" description="Something to do with the velocity of the balls? (called vel internally.)" />
  <Time type="float" default="1" description="Something to do with time, how long between ball spawns?" />
  
  <Extra type="preview_box_x" name="Width" />
  <Extra type="preview_box_y" name="Height" />
  <Extra type="preview_box_z" name="Length" />
</Template>
